{
    "link-external": 10150,
    "ok": 10003,
    "prev": 11164,
    "next": 11166,
    "more": 11167,
    "less": 11165,
    "new-line": 9166,
    "loading": 9676,
    "star": 9733,
    "star-off": 9734,
    "star-half": 11242,
    "flame": 9670,
    "flame-off": 9671,
    "flame-half": 11030,
    "zen": 61697,
    "watch": 61698,
    "warning": 61699,
    "toggle-on": 61700,
    "toggle-off": 61701,
    "symbols": 61702,
    "stats": 61703,
    "speed": 61704,
    "skip": 61705,
    "shift": 61706,
    "shift-off": 61707,
    "settings": 61708,
    "save": 61709,
    "reset": 61710,
    "repeat": 61711,
    "reload": 61712,
    "reading-on": 61713,
    "reading-off": 61714,
    "profile": 61715,
    "pb": 61716,
    "pause": 61717,
    "option": 61718,
    "meta-windows": 61719,
    "meta-macos": 61720,
    "meta-linux": 61721,
    "menu": 61722,
    "logo": 61723,
    "light-mode": 61724,
    "info": 61725,
    "home": 61726,
    "heart": 61727,
    "heart-off": 61728,
    "fullscreen": 61729,
    "fullscreen-off": 61730,
    "extra": 61731,
    "enter": 61732,
    "enter-1": 61733,
    "download": 61734,
    "dark-mode": 61735,
    "close": 61736,
    "books": 61737,
    "bookmark-on": 61738,
    "bookmark-off": 61739,
    "backspace": 61740,
    "backspace-word": 61741,
    "back": 61742,
    "arrow-up": 61743,
    "arrow-right": 61744,
    "arrow-left": 61745,
    "arrow-down": 61746,
    "annotations": 61747,
    "accuracy": 61748
}