{
  "id": "seneca--dialogues",
  "title": "Dialogues",
  "titleAlpha": "dialogues",
  "author": "Seneca",
  "language": "en",
  "description": "Seneca's dialogues and consolations, including \"On Benefits,\" examine living life through the lens of Stoic philosophy.",
  "longDescription": [
    "Seneca the Younger was a statesman and philosopher who lived in Rome around the dawn of the Common Era. Though he wrote a large amount of tragedies and other works, today he's perhaps best known for his writing on Stoic philosophy and principles.",
    "Seneca didn't write books about Stoicism; rather, he composed essays and sent letters over the course of his lifetime that addressed that philosophy. Since these essays and letters are addressed to his friends and contemporaries, they're written in a conversational style, and thus referred to as his \"Dialogues.\" Some were written to friends on the death of their loved ones, in an effort to console and comfort them. Others were written to help friends with their personality flaws, like anger. One, \"On Clemency,\" was addressed to the emperor Nero as an effort to guide him on the path of good statesmanship.",
    "This collection contains all of his dialogues, including the longer \"On Benefits.\""
  ],
  "year": 55,
  "genres": [
    "classics",
    "philosophy",
    "nonfiction"
  ],
  "topics": [
    "empires"
  ],
  "rights": "The source text and artwork in this ebook are believed to be in the United States public domain; that is, they are believed to be free of copyright restrictions in the United States. They may still be copyrighted in other countries, so users located outside of the United States must check their local laws before using this ebook. The creators of, and contributors to, this ebook dedicate their contributions to the worldwide public domain via the terms in the [CC0 1.0 Universal Public Domain Dedication](https://creativecommons.org/publicdomain/zero/1.0/).",
  "publisher": "Standard Ebooks",
  "series": null,
  "part": 0,
  "source": {
    "isUrl": true,
    "value": "https://standardebooks.org/ebooks/seneca/dialogues/aubrey-stewart"
  },
  "chapters": [
    {
      "id": "001",
      "title": "Titlepage - Dialogues",
      "length": 41,
      "mode": "hide"
    },
    {
      "id": "002",
      "title": "Imprint",
      "length": 1215,
      "mode": "hide"
    },
    {
      "id": "003",
      "title": "To Marcia, on Consolation - I",
      "length": 5255,
      "mode": "type"
    },
    {
      "id": "004",
      "title": "To Marcia, on Consolation - II",
      "length": 2941,
      "mode": "type"
    },
    {
      "id": "005",
      "title": "To Marcia, on Consolation - III",
      "length": 3049,
      "mode": "type"
    },
    {
      "id": "006",
      "title": "To Marcia, on Consolation - IV",
      "length": 1991,
      "mode": "type"
    },
    {
      "id": "007",
      "title": "To Marcia, on Consolation - V",
      "length": 2192,
      "mode": "type"
    },
    {
      "id": "008",
      "title": "To Marcia, on Consolation - VI",
      "length": 1374,
      "mode": "type"
    },
    {
      "id": "009",
      "title": "To Marcia, on Consolation - VII",
      "length": 1968,
      "mode": "type"
    },
    {
      "id": "010",
      "title": "To Marcia, on Consolation - VIII",
      "length": 1031,
      "mode": "type"
    },
    {
      "id": "011",
      "title": "To Marcia, on Consolation - IX",
      "length": 2595,
      "mode": "type"
    },
    {
      "id": "012",
      "title": "To Marcia, on Consolation - X",
      "length": 3366,
      "mode": "type"
    },
    {
      "id": "013",
      "title": "To Marcia, on Consolation - XI",
      "length": 3048,
      "mode": "type"
    },
    {
      "id": "014",
      "title": "To Marcia, on Consolation - XII",
      "length": 4354,
      "mode": "type"
    },
    {
      "id": "015",
      "title": "To Marcia, on Consolation - XIII",
      "length": 2276,
      "mode": "type"
    },
    {
      "id": "016",
      "title": "To Marcia, on Consolation - XIV",
      "length": 1833,
      "mode": "type"
    },
    {
      "id": "017",
      "title": "To Marcia, on Consolation - XV",
      "length": 1745,
      "mode": "type"
    },
    {
      "id": "018",
      "title": "To Marcia, on Consolation - XVI",
      "length": 4717,
      "mode": "type"
    },
    {
      "id": "019",
      "title": "To Marcia, on Consolation - XVII",
      "length": 3910,
      "mode": "type"
    },
    {
      "id": "020",
      "title": "To Marcia, on Consolation - XVIII",
      "length": 4284,
      "mode": "type"
    },
    {
      "id": "021",
      "title": "To Marcia, on Consolation - XIX",
      "length": 3434,
      "mode": "type"
    },
    {
      "id": "022",
      "title": "To Marcia, on Consolation - XX",
      "length": 4099,
      "mode": "type"
    },
    {
      "id": "023",
      "title": "To Marcia, on Consolation - XXI",
      "length": 3451,
      "mode": "type"
    },
    {
      "id": "024",
      "title": "To Marcia, on Consolation - XXII",
      "length": 5397,
      "mode": "type"
    },
    {
      "id": "025",
      "title": "To Marcia, on Consolation - XXIII",
      "length": 2398,
      "mode": "type"
    },
    {
      "id": "026",
      "title": "To Marcia, on Consolation - XXIV",
      "length": 2984,
      "mode": "type"
    },
    {
      "id": "027",
      "title": "To Marcia, on Consolation - XXV",
      "length": 2020,
      "mode": "type"
    },
    {
      "id": "028",
      "title": "To Marcia, on Consolation - XXVI",
      "length": 4233,
      "mode": "type"
    },
    {
      "id": "029",
      "title": "On Anger - Book I - I",
      "length": 3041,
      "mode": "type"
    },
    {
      "id": "030",
      "title": "On Anger - Book I - II",
      "length": 2270,
      "mode": "type"
    },
    {
      "id": "031",
      "title": "On Anger - Book I - III",
      "length": 3472,
      "mode": "type"
    },
    {
      "id": "032",
      "title": "On Anger - Book I - IV",
      "length": 1057,
      "mode": "type"
    },
    {
      "id": "033",
      "title": "On Anger - Book I - V",
      "length": 1421,
      "mode": "type"
    },
    {
      "id": "034",
      "title": "On Anger - Book I - VI",
      "length": 3059,
      "mode": "type"
    },
    {
      "id": "035",
      "title": "On Anger - Book I - VII",
      "length": 1970,
      "mode": "type"
    },
    {
      "id": "036",
      "title": "On Anger - Book I - VIII",
      "length": 2616,
      "mode": "type"
    },
    {
      "id": "037",
      "title": "On Anger - Book I - IX",
      "length": 1678,
      "mode": "type"
    },
    {
      "id": "038",
      "title": "On Anger - Book I - X",
      "length": 1444,
      "mode": "type"
    },
    {
      "id": "039",
      "title": "On Anger - Book I - XI",
      "length": 3404,
      "mode": "type"
    },
    {
      "id": "040",
      "title": "On Anger - Book I - XII",
      "length": 2804,
      "mode": "type"
    },
    {
      "id": "041",
      "title": "On Anger - Book I - XIII",
      "length": 1763,
      "mode": "type"
    },
    {
      "id": "042",
      "title": "On Anger - Book I - XIV",
      "length": 1147,
      "mode": "type"
    },
    {
      "id": "043",
      "title": "On Anger - Book I - XV",
      "length": 1637,
      "mode": "type"
    },
    {
      "id": "044",
      "title": "On Anger - Book I - XVI",
      "length": 4098,
      "mode": "type"
    },
    {
      "id": "045",
      "title": "On Anger - Book I - XVII",
      "length": 2804,
      "mode": "type"
    },
    {
      "id": "046",
      "title": "On Anger - Book I - XVIII",
      "length": 2522,
      "mode": "type"
    },
    {
      "id": "047",
      "title": "On Anger - Book I - XIX",
      "length": 3270,
      "mode": "type"
    },
    {
      "id": "048",
      "title": "On Anger - Book I - XX",
      "length": 3695,
      "mode": "type"
    },
    {
      "id": "049",
      "title": "On Anger - Book I - XXI",
      "length": 1341,
      "mode": "type"
    },
    {
      "id": "050",
      "title": "On Anger - Book II - I",
      "length": 1848,
      "mode": "type"
    },
    {
      "id": "051",
      "title": "On Anger - Book II - II",
      "length": 2304,
      "mode": "type"
    },
    {
      "id": "052",
      "title": "On Anger - Book II - III",
      "length": 2130,
      "mode": "type"
    },
    {
      "id": "053",
      "title": "On Anger - Book II - IV",
      "length": 1118,
      "mode": "type"
    },
    {
      "id": "054",
      "title": "On Anger - Book II - V",
      "length": 1901,
      "mode": "type"
    },
    {
      "id": "055",
      "title": "On Anger - Book II - VI",
      "length": 1462,
      "mode": "type"
    },
    {
      "id": "056",
      "title": "On Anger - Book II - VII",
      "length": 1399,
      "mode": "type"
    },
    {
      "id": "057",
      "title": "On Anger - Book II - VIII",
      "length": 1177,
      "mode": "type"
    },
    {
      "id": "058",
      "title": "On Anger - Book II - IX",
      "length": 2121,
      "mode": "type"
    },
    {
      "id": "059",
      "title": "On Anger - Book II - X",
      "length": 3637,
      "mode": "type"
    },
    {
      "id": "060",
      "title": "On Anger - Book II - XI",
      "length": 2537,
      "mode": "type"
    },
    {
      "id": "061",
      "title": "On Anger - Book II - XII",
      "length": 2511,
      "mode": "type"
    },
    {
      "id": "062",
      "title": "On Anger - Book II - XIII",
      "length": 1502,
      "mode": "type"
    },
    {
      "id": "063",
      "title": "On Anger - Book II - XIV",
      "length": 1508,
      "mode": "type"
    },
    {
      "id": "064",
      "title": "On Anger - Book II - XV",
      "length": 1702,
      "mode": "type"
    },
    {
      "id": "065",
      "title": "On Anger - Book II - XVI",
      "length": 1216,
      "mode": "type"
    },
    {
      "id": "066",
      "title": "On Anger - Book II - XVII",
      "length": 975,
      "mode": "type"
    },
    {
      "id": "067",
      "title": "On Anger - Book II - XVIII",
      "length": 877,
      "mode": "type"
    },
    {
      "id": "068",
      "title": "On Anger - Book II - XIX",
      "length": 2295,
      "mode": "type"
    },
    {
      "id": "069",
      "title": "On Anger - Book II - XX",
      "length": 1775,
      "mode": "type"
    },
    {
      "id": "070",
      "title": "On Anger - Book II - XXI",
      "length": 3744,
      "mode": "type"
    },
    {
      "id": "071",
      "title": "On Anger - Book II - XXII",
      "length": 1235,
      "mode": "type"
    },
    {
      "id": "072",
      "title": "On Anger - Book II - XXIII",
      "length": 1535,
      "mode": "type"
    },
    {
      "id": "073",
      "title": "On Anger - Book II - XXIV",
      "length": 845,
      "mode": "type"
    },
    {
      "id": "074",
      "title": "On Anger - Book II - XXV",
      "length": 1826,
      "mode": "type"
    },
    {
      "id": "075",
      "title": "On Anger - Book II - XXVI",
      "length": 1904,
      "mode": "type"
    },
    {
      "id": "076",
      "title": "On Anger - Book II - XXVII",
      "length": 1602,
      "mode": "type"
    },
    {
      "id": "077",
      "title": "On Anger - Book II - XXVIII",
      "length": 4008,
      "mode": "type"
    },
    {
      "id": "078",
      "title": "On Anger - Book II - XXIX",
      "length": 2129,
      "mode": "type"
    },
    {
      "id": "079",
      "title": "On Anger - Book II - XXX",
      "length": 1468,
      "mode": "type"
    },
    {
      "id": "080",
      "title": "On Anger - Book II - XXXI",
      "length": 3838,
      "mode": "type"
    },
    {
      "id": "081",
      "title": "On Anger - Book II - XXXII",
      "length": 1319,
      "mode": "type"
    },
    {
      "id": "082",
      "title": "On Anger - Book II - XXXIII",
      "length": 3047,
      "mode": "type"
    },
    {
      "id": "083",
      "title": "On Anger - Book II - XXXIV",
      "length": 2098,
      "mode": "type"
    },
    {
      "id": "084",
      "title": "On Anger - Book II - XXXV",
      "length": 3095,
      "mode": "type"
    },
    {
      "id": "085",
      "title": "On Anger - Book II - XXXVI",
      "length": 2875,
      "mode": "type"
    },
    {
      "id": "086",
      "title": "On Anger - Book III - I",
      "length": 2532,
      "mode": "type"
    },
    {
      "id": "087",
      "title": "On Anger - Book III - II",
      "length": 2745,
      "mode": "type"
    },
    {
      "id": "088",
      "title": "On Anger - Book III - III",
      "length": 2385,
      "mode": "type"
    },
    {
      "id": "089",
      "title": "On Anger - Book III - IV",
      "length": 1988,
      "mode": "type"
    },
    {
      "id": "090",
      "title": "On Anger - Book III - V",
      "length": 3628,
      "mode": "type"
    },
    {
      "id": "091",
      "title": "On Anger - Book III - VI",
      "length": 2801,
      "mode": "type"
    },
    {
      "id": "092",
      "title": "On Anger - Book III - VII",
      "length": 1300,
      "mode": "type"
    },
    {
      "id": "093",
      "title": "On Anger - Book III - VIII",
      "length": 3595,
      "mode": "type"
    },
    {
      "id": "094",
      "title": "On Anger - Book III - IX",
      "length": 1961,
      "mode": "type"
    },
    {
      "id": "095",
      "title": "On Anger - Book III - X",
      "length": 1828,
      "mode": "type"
    },
    {
      "id": "096",
      "title": "On Anger - Book III - XI",
      "length": 1433,
      "mode": "type"
    },
    {
      "id": "097",
      "title": "On Anger - Book III - XII",
      "length": 3235,
      "mode": "type"
    },
    {
      "id": "098",
      "title": "On Anger - Book III - XIII",
      "length": 2669,
      "mode": "type"
    },
    {
      "id": "099",
      "title": "On Anger - Book III - XIV",
      "length": 2644,
      "mode": "type"
    },
    {
      "id": "100",
      "title": "On Anger - Book III - XV",
      "length": 2613,
      "mode": "type"
    },
    {
      "id": "101",
      "title": "On Anger - Book III - XVI",
      "length": 2586,
      "mode": "type"
    },
    {
      "id": "102",
      "title": "On Anger - Book III - XVII",
      "length": 1432,
      "mode": "type"
    },
    {
      "id": "103",
      "title": "On Anger - Book III - XVIII",
      "length": 1974,
      "mode": "type"
    },
    {
      "id": "104",
      "title": "On Anger - Book III - XIX",
      "length": 2477,
      "mode": "type"
    },
    {
      "id": "105",
      "title": "On Anger - Book III - XX",
      "length": 1785,
      "mode": "type"
    },
    {
      "id": "106",
      "title": "On Anger - Book III - XXI",
      "length": 1597,
      "mode": "type"
    },
    {
      "id": "107",
      "title": "On Anger - Book III - XXII",
      "length": 1917,
      "mode": "type"
    },
    {
      "id": "108",
      "title": "On Anger - Book III - XXIII",
      "length": 2812,
      "mode": "type"
    },
    {
      "id": "109",
      "title": "On Anger - Book III - XXIV",
      "length": 1524,
      "mode": "type"
    },
    {
      "id": "110",
      "title": "On Anger - Book III - XXV",
      "length": 1817,
      "mode": "type"
    },
    {
      "id": "111",
      "title": "On Anger - Book III - XXVI",
      "length": 2348,
      "mode": "type"
    },
    {
      "id": "112",
      "title": "On Anger - Book III - XXVII",
      "length": 1913,
      "mode": "type"
    },
    {
      "id": "113",
      "title": "On Anger - Book III - XXVIII",
      "length": 2643,
      "mode": "type"
    },
    {
      "id": "114",
      "title": "On Anger - Book III - XXIX",
      "length": 1218,
      "mode": "type"
    },
    {
      "id": "115",
      "title": "On Anger - Book III - XXX",
      "length": 2108,
      "mode": "type"
    },
    {
      "id": "116",
      "title": "On Anger - Book III - XXXI",
      "length": 1568,
      "mode": "type"
    },
    {
      "id": "117",
      "title": "On Anger - Book III - XXXII",
      "length": 1270,
      "mode": "type"
    },
    {
      "id": "118",
      "title": "On Anger - Book III - XXXIII",
      "length": 1642,
      "mode": "type"
    },
    {
      "id": "119",
      "title": "On Anger - Book III - XXXIV",
      "length": 1307,
      "mode": "type"
    },
    {
      "id": "120",
      "title": "On Anger - Book III - XXXV",
      "length": 2080,
      "mode": "type"
    },
    {
      "id": "121",
      "title": "On Anger - Book III - XXXVI",
      "length": 1868,
      "mode": "type"
    },
    {
      "id": "122",
      "title": "On Anger - Book III - XXXVII",
      "length": 1881,
      "mode": "type"
    },
    {
      "id": "123",
      "title": "On Anger - Book III - XXXVIII",
      "length": 639,
      "mode": "type"
    },
    {
      "id": "124",
      "title": "On Anger - Book III - XXXIX",
      "length": 1908,
      "mode": "type"
    },
    {
      "id": "125",
      "title": "On Anger - Book III - XL",
      "length": 1838,
      "mode": "type"
    },
    {
      "id": "126",
      "title": "On Anger - Book III - XLI",
      "length": 1382,
      "mode": "type"
    },
    {
      "id": "127",
      "title": "On Anger - Book III - XLII",
      "length": 1465,
      "mode": "type"
    },
    {
      "id": "128",
      "title": "On Anger - Book III - XLIII",
      "length": 2580,
      "mode": "type"
    },
    {
      "id": "129",
      "title": "To Helvia, on Consolation - I",
      "length": 2230,
      "mode": "type"
    },
    {
      "id": "130",
      "title": "To Helvia, on Consolation - II",
      "length": 2770,
      "mode": "type"
    },
    {
      "id": "131",
      "title": "To Helvia, on Consolation - III",
      "length": 794,
      "mode": "type"
    },
    {
      "id": "132",
      "title": "To Helvia, on Consolation - IV",
      "length": 1117,
      "mode": "type"
    },
    {
      "id": "133",
      "title": "To Helvia, on Consolation - V",
      "length": 3263,
      "mode": "type"
    },
    {
      "id": "134",
      "title": "To Helvia, on Consolation - VI",
      "length": 4209,
      "mode": "type"
    },
    {
      "id": "135",
      "title": "To Helvia, on Consolation - VII",
      "length": 5183,
      "mode": "type"
    },
    {
      "id": "136",
      "title": "To Helvia, on Consolation - VIII",
      "length": 2685,
      "mode": "type"
    },
    {
      "id": "137",
      "title": "To Helvia, on Consolation - IX",
      "length": 4122,
      "mode": "type"
    },
    {
      "id": "138",
      "title": "To Helvia, on Consolation - X",
      "length": 6390,
      "mode": "type"
    },
    {
      "id": "139",
      "title": "To Helvia, on Consolation - XI",
      "length": 3023,
      "mode": "type"
    },
    {
      "id": "140",
      "title": "To Helvia, on Consolation - XII",
      "length": 3372,
      "mode": "type"
    },
    {
      "id": "141",
      "title": "To Helvia, on Consolation - XIII",
      "length": 3404,
      "mode": "type"
    },
    {
      "id": "142",
      "title": "To Helvia, on Consolation - XIV",
      "length": 1574,
      "mode": "type"
    },
    {
      "id": "143",
      "title": "To Helvia, on Consolation - XV",
      "length": 1956,
      "mode": "type"
    },
    {
      "id": "144",
      "title": "To Helvia, on Consolation - XVI",
      "length": 4018,
      "mode": "type"
    },
    {
      "id": "145",
      "title": "To Helvia, on Consolation - XVII",
      "length": 2865,
      "mode": "type"
    },
    {
      "id": "146",
      "title": "To Helvia, on Consolation - XVIII",
      "length": 3791,
      "mode": "type"
    },
    {
      "id": "147",
      "title": "To Helvia, on Consolation - XIX",
      "length": 4227,
      "mode": "type"
    },
    {
      "id": "148",
      "title": "To Helvia, on Consolation - XX",
      "length": 1277,
      "mode": "type"
    },
    {
      "id": "149",
      "title": "To Polybius, on Consolation - I",
      "length": 1807,
      "mode": "type"
    },
    {
      "id": "150",
      "title": "To Polybius, on Consolation - II",
      "length": 2996,
      "mode": "type"
    },
    {
      "id": "151",
      "title": "To Polybius, on Consolation - III",
      "length": 2326,
      "mode": "type"
    },
    {
      "id": "152",
      "title": "To Polybius, on Consolation - IV",
      "length": 1740,
      "mode": "type"
    },
    {
      "id": "153",
      "title": "To Polybius, on Consolation - V",
      "length": 2770,
      "mode": "type"
    },
    {
      "id": "154",
      "title": "To Polybius, on Consolation - VI",
      "length": 3110,
      "mode": "type"
    },
    {
      "id": "155",
      "title": "To Polybius, on Consolation - VII",
      "length": 1653,
      "mode": "type"
    },
    {
      "id": "156",
      "title": "To Polybius, on Consolation - VIII",
      "length": 2203,
      "mode": "type"
    },
    {
      "id": "157",
      "title": "To Polybius, on Consolation - IX",
      "length": 4664,
      "mode": "type"
    },
    {
      "id": "158",
      "title": "To Polybius, on Consolation - X",
      "length": 2878,
      "mode": "type"
    },
    {
      "id": "159",
      "title": "To Polybius, on Consolation - XI",
      "length": 3507,
      "mode": "type"
    },
    {
      "id": "160",
      "title": "To Polybius, on Consolation - XII",
      "length": 2597,
      "mode": "type"
    },
    {
      "id": "161",
      "title": "To Polybius, on Consolation - XIII",
      "length": 2189,
      "mode": "type"
    },
    {
      "id": "162",
      "title": "To Polybius, on Consolation - XIV",
      "length": 2358,
      "mode": "type"
    },
    {
      "id": "163",
      "title": "To Polybius, on Consolation - XV",
      "length": 2763,
      "mode": "type"
    },
    {
      "id": "164",
      "title": "To Polybius, on Consolation - XVI",
      "length": 2906,
      "mode": "type"
    },
    {
      "id": "165",
      "title": "To Polybius, on Consolation - XVII",
      "length": 2881,
      "mode": "type"
    },
    {
      "id": "166",
      "title": "To Polybius, on Consolation - XVIII",
      "length": 4577,
      "mode": "type"
    },
    {
      "id": "167",
      "title": "On the Shortness of Life - I",
      "length": 1730,
      "mode": "type"
    },
    {
      "id": "168",
      "title": "On the Shortness of Life - II",
      "length": 3406,
      "mode": "type"
    },
    {
      "id": "169",
      "title": "On the Shortness of Life - III",
      "length": 3228,
      "mode": "type"
    },
    {
      "id": "170",
      "title": "On the Shortness of Life - IV",
      "length": 2856,
      "mode": "type"
    },
    {
      "id": "171",
      "title": "On the Shortness of Life - V",
      "length": 1165,
      "mode": "type"
    },
    {
      "id": "172",
      "title": "On the Shortness of Life - VI",
      "length": 2235,
      "mode": "type"
    },
    {
      "id": "173",
      "title": "On the Shortness of Life - VII",
      "length": 5108,
      "mode": "type"
    },
    {
      "id": "174",
      "title": "On the Shortness of Life - VIII",
      "length": 2567,
      "mode": "type"
    },
    {
      "id": "175",
      "title": "On the Shortness of Life - IX",
      "length": 2366,
      "mode": "type"
    },
    {
      "id": "176",
      "title": "On the Shortness of Life - X",
      "length": 3278,
      "mode": "type"
    },
    {
      "id": "177",
      "title": "On the Shortness of Life - XI",
      "length": 1351,
      "mode": "type"
    },
    {
      "id": "178",
      "title": "On the Shortness of Life - XII",
      "length": 5251,
      "mode": "type"
    },
    {
      "id": "179",
      "title": "On the Shortness of Life - XIII",
      "length": 5010,
      "mode": "type"
    },
    {
      "id": "180",
      "title": "On the Shortness of Life - XIV",
      "length": 2868,
      "mode": "type"
    },
    {
      "id": "181",
      "title": "On the Shortness of Life - XV",
      "length": 2294,
      "mode": "type"
    },
    {
      "id": "182",
      "title": "On the Shortness of Life - XVI",
      "length": 2072,
      "mode": "type"
    },
    {
      "id": "183",
      "title": "On the Shortness of Life - XVII",
      "length": 3532,
      "mode": "type"
    },
    {
      "id": "184",
      "title": "On the Shortness of Life - XVIII",
      "length": 3120,
      "mode": "type"
    },
    {
      "id": "185",
      "title": "On the Shortness of Life - XIX",
      "length": 1656,
      "mode": "type"
    },
    {
      "id": "186",
      "title": "On the Shortness of Life - XX",
      "length": 2782,
      "mode": "type"
    },
    {
      "id": "187",
      "title": "On Leisure - I",
      "length": 2615,
      "mode": "type"
    },
    {
      "id": "188",
      "title": "On Leisure - II",
      "length": 770,
      "mode": "type"
    },
    {
      "id": "189",
      "title": "On Leisure - III",
      "length": 2472,
      "mode": "type"
    },
    {
      "id": "190",
      "title": "On Leisure - IV",
      "length": 1530,
      "mode": "type"
    },
    {
      "id": "191",
      "title": "On Leisure - V",
      "length": 4509,
      "mode": "type"
    },
    {
      "id": "192",
      "title": "On Leisure - VI",
      "length": 2650,
      "mode": "type"
    },
    {
      "id": "193",
      "title": "On Leisure - VII",
      "length": 1711,
      "mode": "type"
    },
    {
      "id": "194",
      "title": "On Leisure - VIII",
      "length": 1834,
      "mode": "type"
    },
    {
      "id": "195",
      "title": "On Peace of Mind - I: (Serenus)",
      "length": 8103,
      "mode": "type"
    },
    {
      "id": "196",
      "title": "On Peace of Mind - II: (Seneca)",
      "length": 8872,
      "mode": "type"
    },
    {
      "id": "197",
      "title": "On Peace of Mind - III",
      "length": 4235,
      "mode": "type"
    },
    {
      "id": "198",
      "title": "On Peace of Mind - IV",
      "length": 3796,
      "mode": "type"
    },
    {
      "id": "199",
      "title": "On Peace of Mind - V",
      "length": 2639,
      "mode": "type"
    },
    {
      "id": "200",
      "title": "On Peace of Mind - VI",
      "length": 1774,
      "mode": "type"
    },
    {
      "id": "201",
      "title": "On Peace of Mind - VII",
      "length": 3429,
      "mode": "type"
    },
    {
      "id": "202",
      "title": "On Peace of Mind - VIII",
      "length": 3897,
      "mode": "type"
    },
    {
      "id": "203",
      "title": "On Peace of Mind - IX",
      "length": 4131,
      "mode": "type"
    },
    {
      "id": "204",
      "title": "On Peace of Mind - X",
      "length": 3974,
      "mode": "type"
    },
    {
      "id": "205",
      "title": "On Peace of Mind - XI",
      "length": 7060,
      "mode": "type"
    },
    {
      "id": "206",
      "title": "On Peace of Mind - XII",
      "length": 3010,
      "mode": "type"
    },
    {
      "id": "207",
      "title": "On Peace of Mind - XIII",
      "length": 1242,
      "mode": "type"
    },
    {
      "id": "208",
      "title": "On Peace of Mind - XIV",
      "length": 4440,
      "mode": "type"
    },
    {
      "id": "209",
      "title": "On Peace of Mind - XV",
      "length": 2853,
      "mode": "type"
    },
    {
      "id": "210",
      "title": "On Peace of Mind - XVI",
      "length": 1951,
      "mode": "type"
    },
    {
      "id": "211",
      "title": "On Peace of Mind - XVII",
      "length": 6838,
      "mode": "type"
    },
    {
      "id": "212",
      "title": "On Providence - I",
      "length": 3780,
      "mode": "type"
    },
    {
      "id": "213",
      "title": "On Providence - II",
      "length": 5481,
      "mode": "type"
    },
    {
      "id": "214",
      "title": "On Providence - III",
      "length": 8368,
      "mode": "type"
    },
    {
      "id": "215",
      "title": "On Providence - IV",
      "length": 8222,
      "mode": "type"
    },
    {
      "id": "216",
      "title": "On Providence - V",
      "length": 6438,
      "mode": "type"
    },
    {
      "id": "217",
      "title": "On Providence - VI",
      "length": 4836,
      "mode": "type"
    },
    {
      "id": "218",
      "title": "On the Firmness of the Wise Person - I",
      "length": 1928,
      "mode": "type"
    },
    {
      "id": "219",
      "title": "On the Firmness of the Wise Person - II",
      "length": 1927,
      "mode": "type"
    },
    {
      "id": "220",
      "title": "On the Firmness of the Wise Person - III",
      "length": 3427,
      "mode": "type"
    },
    {
      "id": "221",
      "title": "On the Firmness of the Wise Person - IV",
      "length": 1645,
      "mode": "type"
    },
    {
      "id": "222",
      "title": "On the Firmness of the Wise Person - V",
      "length": 3825,
      "mode": "type"
    },
    {
      "id": "223",
      "title": "On the Firmness of the Wise Person - VI",
      "length": 3474,
      "mode": "type"
    },
    {
      "id": "224",
      "title": "On the Firmness of the Wise Person - VII",
      "length": 3022,
      "mode": "type"
    },
    {
      "id": "225",
      "title": "On the Firmness of the Wise Person - VIII",
      "length": 2098,
      "mode": "type"
    },
    {
      "id": "226",
      "title": "On the Firmness of the Wise Person - IX",
      "length": 2725,
      "mode": "type"
    },
    {
      "id": "227",
      "title": "On the Firmness of the Wise Person - X",
      "length": 2481,
      "mode": "type"
    },
    {
      "id": "228",
      "title": "On the Firmness of the Wise Person - XI",
      "length": 1784,
      "mode": "type"
    },
    {
      "id": "229",
      "title": "On the Firmness of the Wise Person - XII",
      "length": 2071,
      "mode": "type"
    },
    {
      "id": "230",
      "title": "On the Firmness of the Wise Person - XIII",
      "length": 3050,
      "mode": "type"
    },
    {
      "id": "231",
      "title": "On the Firmness of the Wise Person - XIV",
      "length": 2264,
      "mode": "type"
    },
    {
      "id": "232",
      "title": "On the Firmness of the Wise Person - XV",
      "length": 2002,
      "mode": "type"
    },
    {
      "id": "233",
      "title": "On the Firmness of the Wise Person - XVI",
      "length": 2139,
      "mode": "type"
    },
    {
      "id": "234",
      "title": "On the Firmness of the Wise Person - XVII",
      "length": 1921,
      "mode": "type"
    },
    {
      "id": "235",
      "title": "On the Firmness of the Wise Person - XVIII",
      "length": 3270,
      "mode": "type"
    },
    {
      "id": "236",
      "title": "On the Firmness of the Wise Person - XIX",
      "length": 2802,
      "mode": "type"
    },
    {
      "id": "237",
      "title": "On a Happy Life - I",
      "length": 3211,
      "mode": "type"
    },
    {
      "id": "238",
      "title": "On a Happy Life - II",
      "length": 2434,
      "mode": "type"
    },
    {
      "id": "239",
      "title": "On a Happy Life - III",
      "length": 2295,
      "mode": "type"
    },
    {
      "id": "240",
      "title": "On a Happy Life - IV",
      "length": 3045,
      "mode": "type"
    },
    {
      "id": "241",
      "title": "On a Happy Life - V",
      "length": 1493,
      "mode": "type"
    },
    {
      "id": "242",
      "title": "On a Happy Life - VI",
      "length": 1170,
      "mode": "type"
    },
    {
      "id": "243",
      "title": "On a Happy Life - VII",
      "length": 2600,
      "mode": "type"
    },
    {
      "id": "244",
      "title": "On a Happy Life - VIII",
      "length": 3225,
      "mode": "type"
    },
    {
      "id": "245",
      "title": "On a Happy Life - IX",
      "length": 1857,
      "mode": "type"
    },
    {
      "id": "246",
      "title": "On a Happy Life - X",
      "length": 1568,
      "mode": "type"
    },
    {
      "id": "247",
      "title": "On a Happy Life - XI",
      "length": 2178,
      "mode": "type"
    },
    {
      "id": "248",
      "title": "On a Happy Life - XII",
      "length": 2281,
      "mode": "type"
    },
    {
      "id": "249",
      "title": "On a Happy Life - XIII",
      "length": 2797,
      "mode": "type"
    },
    {
      "id": "250",
      "title": "On a Happy Life - XIV",
      "length": 1771,
      "mode": "type"
    },
    {
      "id": "251",
      "title": "On a Happy Life - XV",
      "length": 3340,
      "mode": "type"
    },
    {
      "id": "252",
      "title": "On a Happy Life - XVI",
      "length": 1662,
      "mode": "type"
    },
    {
      "id": "253",
      "title": "On a Happy Life - XVII",
      "length": 2256,
      "mode": "type"
    },
    {
      "id": "254",
      "title": "On a Happy Life - XVIII",
      "length": 1376,
      "mode": "type"
    },
    {
      "id": "255",
      "title": "On a Happy Life - XIX",
      "length": 1960,
      "mode": "type"
    },
    {
      "id": "256",
      "title": "On a Happy Life - XX",
      "length": 3692,
      "mode": "type"
    },
    {
      "id": "257",
      "title": "On a Happy Life - XXI",
      "length": 1927,
      "mode": "type"
    },
    {
      "id": "258",
      "title": "On a Happy Life - XXII",
      "length": 2081,
      "mode": "type"
    },
    {
      "id": "259",
      "title": "On a Happy Life - XXIII",
      "length": 2906,
      "mode": "type"
    },
    {
      "id": "260",
      "title": "On a Happy Life - XXIV",
      "length": 3409,
      "mode": "type"
    },
    {
      "id": "261",
      "title": "On a Happy Life - XXV",
      "length": 4215,
      "mode": "type"
    },
    {
      "id": "262",
      "title": "On a Happy Life - XXVI",
      "length": 4370,
      "mode": "type"
    },
    {
      "id": "263",
      "title": "On a Happy Life - XXVII",
      "length": 2674,
      "mode": "type"
    },
    {
      "id": "264",
      "title": "On a Happy Life - XXVIII",
      "length": 678,
      "mode": "type"
    },
    {
      "id": "265",
      "title": "On Clemency - Book I - I",
      "length": 5347,
      "mode": "type"
    },
    {
      "id": "266",
      "title": "On Clemency - Book I - II",
      "length": 1430,
      "mode": "type"
    },
    {
      "id": "267",
      "title": "On Clemency - Book I - III",
      "length": 3189,
      "mode": "type"
    },
    {
      "id": "268",
      "title": "On Clemency - Book I - IV",
      "length": 1580,
      "mode": "type"
    },
    {
      "id": "269",
      "title": "On Clemency - Book I - V",
      "length": 3438,
      "mode": "type"
    },
    {
      "id": "270",
      "title": "On Clemency - Book I - VI",
      "length": 1246,
      "mode": "type"
    },
    {
      "id": "271",
      "title": "On Clemency - Book I - VII",
      "length": 1865,
      "mode": "type"
    },
    {
      "id": "272",
      "title": "On Clemency - Book I - VIII",
      "length": 2838,
      "mode": "type"
    },
    {
      "id": "273",
      "title": "On Clemency - Book I - IX",
      "length": 5924,
      "mode": "type"
    },
    {
      "id": "274",
      "title": "On Clemency - Book I - X",
      "length": 1927,
      "mode": "type"
    },
    {
      "id": "275",
      "title": "On Clemency - Book I - XI",
      "length": 2080,
      "mode": "type"
    },
    {
      "id": "276",
      "title": "On Clemency - Book I - XII",
      "length": 2879,
      "mode": "type"
    },
    {
      "id": "277",
      "title": "On Clemency - Book I - XIII",
      "length": 3188,
      "mode": "type"
    },
    {
      "id": "278",
      "title": "On Clemency - Book I - XIV",
      "length": 1722,
      "mode": "type"
    },
    {
      "id": "279",
      "title": "On Clemency - Book I - XV",
      "length": 2943,
      "mode": "type"
    },
    {
      "id": "280",
      "title": "On Clemency - Book I - XVI",
      "length": 1972,
      "mode": "type"
    },
    {
      "id": "281",
      "title": "On Clemency - Book I - XVII",
      "length": 1336,
      "mode": "type"
    },
    {
      "id": "282",
      "title": "On Clemency - Book I - XVIII",
      "length": 1618,
      "mode": "type"
    },
    {
      "id": "283",
      "title": "On Clemency - Book I - XIX",
      "length": 4304,
      "mode": "type"
    },
    {
      "id": "284",
      "title": "On Clemency - Book I - XX",
      "length": 1525,
      "mode": "type"
    },
    {
      "id": "285",
      "title": "On Clemency - Book I - XXI",
      "length": 2452,
      "mode": "type"
    },
    {
      "id": "286",
      "title": "On Clemency - Book I - XXII",
      "length": 1405,
      "mode": "type"
    },
    {
      "id": "287",
      "title": "On Clemency - Book I - XXIII",
      "length": 1189,
      "mode": "type"
    },
    {
      "id": "288",
      "title": "On Clemency - Book I - XXIV",
      "length": 877,
      "mode": "type"
    },
    {
      "id": "289",
      "title": "On Clemency - Book I - XXV",
      "length": 2690,
      "mode": "type"
    },
    {
      "id": "290",
      "title": "On Clemency - Book I - XXVI",
      "length": 2939,
      "mode": "type"
    },
    {
      "id": "291",
      "title": "On Clemency - Book II - I",
      "length": 1696,
      "mode": "type"
    },
    {
      "id": "292",
      "title": "On Clemency - Book II - II",
      "length": 1873,
      "mode": "type"
    },
    {
      "id": "293",
      "title": "On Clemency - Book II - III",
      "length": 1043,
      "mode": "type"
    },
    {
      "id": "294",
      "title": "On Clemency - Book II - IV",
      "length": 1978,
      "mode": "type"
    },
    {
      "id": "295",
      "title": "On Clemency - Book II - V",
      "length": 2146,
      "mode": "type"
    },
    {
      "id": "296",
      "title": "On Clemency - Book II - VI",
      "length": 2569,
      "mode": "type"
    },
    {
      "id": "297",
      "title": "On Clemency - Book II - VII",
      "length": 3181,
      "mode": "type"
    },
    {
      "id": "298",
      "title": "On Benefits - Book I - I",
      "length": 6066,
      "mode": "type"
    },
    {
      "id": "299",
      "title": "On Benefits - Book I - II",
      "length": 2211,
      "mode": "type"
    },
    {
      "id": "300",
      "title": "On Benefits - Book I - III",
      "length": 4361,
      "mode": "type"
    },
    {
      "id": "301",
      "title": "On Benefits - Book I - IV",
      "length": 2328,
      "mode": "type"
    },
    {
      "id": "302",
      "title": "On Benefits - Book I - V",
      "length": 2244,
      "mode": "type"
    },
    {
      "id": "303",
      "title": "On Benefits - Book I - VI",
      "length": 1341,
      "mode": "type"
    },
    {
      "id": "304",
      "title": "On Benefits - Book I - VII",
      "length": 1298,
      "mode": "type"
    },
    {
      "id": "305",
      "title": "On Benefits - Book I - VIII",
      "length": 821,
      "mode": "type"
    },
    {
      "id": "306",
      "title": "On Benefits - Book I - IX",
      "length": 2351,
      "mode": "type"
    },
    {
      "id": "307",
      "title": "On Benefits - Book I - X",
      "length": 2938,
      "mode": "type"
    },
    {
      "id": "308",
      "title": "On Benefits - Book I - XI",
      "length": 3290,
      "mode": "type"
    },
    {
      "id": "309",
      "title": "On Benefits - Book I - XII",
      "length": 2014,
      "mode": "type"
    },
    {
      "id": "310",
      "title": "On Benefits - Book I - XIII",
      "length": 1627,
      "mode": "type"
    },
    {
      "id": "311",
      "title": "On Benefits - Book I - XIV",
      "length": 2166,
      "mode": "type"
    },
    {
      "id": "312",
      "title": "On Benefits - Book I - XV",
      "length": 2253,
      "mode": "type"
    },
    {
      "id": "313",
      "title": "On Benefits - Book II - I",
      "length": 2000,
      "mode": "type"
    },
    {
      "id": "314",
      "title": "On Benefits - Book II - II",
      "length": 1354,
      "mode": "type"
    },
    {
      "id": "315",
      "title": "On Benefits - Book II - III",
      "length": 1233,
      "mode": "type"
    },
    {
      "id": "316",
      "title": "On Benefits - Book II - IV",
      "length": 1161,
      "mode": "type"
    },
    {
      "id": "317",
      "title": "On Benefits - Book II - V",
      "length": 2070,
      "mode": "type"
    },
    {
      "id": "318",
      "title": "On Benefits - Book II - VI",
      "length": 1026,
      "mode": "type"
    },
    {
      "id": "319",
      "title": "On Benefits - Book II - VII",
      "length": 1178,
      "mode": "type"
    },
    {
      "id": "320",
      "title": "On Benefits - Book II - VIII",
      "length": 769,
      "mode": "type"
    },
    {
      "id": "321",
      "title": "On Benefits - Book II - IX",
      "length": 532,
      "mode": "type"
    },
    {
      "id": "322",
      "title": "On Benefits - Book II - X",
      "length": 2289,
      "mode": "type"
    },
    {
      "id": "323",
      "title": "On Benefits - Book II - XI",
      "length": 3504,
      "mode": "type"
    },
    {
      "id": "324",
      "title": "On Benefits - Book II - XII",
      "length": 1263,
      "mode": "type"
    },
    {
      "id": "325",
      "title": "On Benefits - Book II - XIII",
      "length": 1258,
      "mode": "type"
    },
    {
      "id": "326",
      "title": "On Benefits - Book II - XIV",
      "length": 2652,
      "mode": "type"
    },
    {
      "id": "327",
      "title": "On Benefits - Book II - XV",
      "length": 1397,
      "mode": "type"
    },
    {
      "id": "328",
      "title": "On Benefits - Book II - XVI",
      "length": 1294,
      "mode": "type"
    },
    {
      "id": "329",
      "title": "On Benefits - Book II - XVII",
      "length": 3557,
      "mode": "type"
    },
    {
      "id": "330",
      "title": "On Benefits - Book II - XVIII",
      "length": 4469,
      "mode": "type"
    },
    {
      "id": "331",
      "title": "On Benefits - Book II - XIX",
      "length": 917,
      "mode": "type"
    },
    {
      "id": "332",
      "title": "On Benefits - Book II - XX",
      "length": 1669,
      "mode": "type"
    },
    {
      "id": "333",
      "title": "On Benefits - Book II - XXI",
      "length": 2634,
      "mode": "type"
    },
    {
      "id": "334",
      "title": "On Benefits - Book II - XXII",
      "length": 521,
      "mode": "type"
    },
    {
      "id": "335",
      "title": "On Benefits - Book II - XXIII",
      "length": 1222,
      "mode": "type"
    },
    {
      "id": "336",
      "title": "On Benefits - Book II - XXIV",
      "length": 1683,
      "mode": "type"
    },
    {
      "id": "337",
      "title": "On Benefits - Book II - XXV",
      "length": 1214,
      "mode": "type"
    },
    {
      "id": "338",
      "title": "On Benefits - Book II - XXVI",
      "length": 861,
      "mode": "type"
    },
    {
      "id": "339",
      "title": "On Benefits - Book II - XXVII",
      "length": 1943,
      "mode": "type"
    },
    {
      "id": "340",
      "title": "On Benefits - Book II - XXVIII",
      "length": 1713,
      "mode": "type"
    },
    {
      "id": "341",
      "title": "On Benefits - Book II - XXIX",
      "length": 2597,
      "mode": "type"
    },
    {
      "id": "342",
      "title": "On Benefits - Book II - XXX",
      "length": 1351,
      "mode": "type"
    },
    {
      "id": "343",
      "title": "On Benefits - Book II - XXXI",
      "length": 1944,
      "mode": "type"
    },
    {
      "id": "344",
      "title": "On Benefits - Book II - XXXII",
      "length": 1428,
      "mode": "type"
    },
    {
      "id": "345",
      "title": "On Benefits - Book II - XXXIII",
      "length": 1583,
      "mode": "type"
    },
    {
      "id": "346",
      "title": "On Benefits - Book II - XXXIV",
      "length": 2005,
      "mode": "type"
    },
    {
      "id": "347",
      "title": "On Benefits - Book II - XXXV",
      "length": 2768,
      "mode": "type"
    },
    {
      "id": "348",
      "title": "On Benefits - Book III - I",
      "length": 2095,
      "mode": "type"
    },
    {
      "id": "349",
      "title": "On Benefits - Book III - II",
      "length": 1144,
      "mode": "type"
    },
    {
      "id": "350",
      "title": "On Benefits - Book III - III",
      "length": 1760,
      "mode": "type"
    },
    {
      "id": "351",
      "title": "On Benefits - Book III - IV",
      "length": 703,
      "mode": "type"
    },
    {
      "id": "352",
      "title": "On Benefits - Book III - V",
      "length": 1317,
      "mode": "type"
    },
    {
      "id": "353",
      "title": "On Benefits - Book III - VI",
      "length": 1298,
      "mode": "type"
    },
    {
      "id": "354",
      "title": "On Benefits - Book III - VII",
      "length": 3001,
      "mode": "type"
    },
    {
      "id": "355",
      "title": "On Benefits - Book III - VIII",
      "length": 2083,
      "mode": "type"
    },
    {
      "id": "356",
      "title": "On Benefits - Book III - IX",
      "length": 1470,
      "mode": "type"
    },
    {
      "id": "357",
      "title": "On Benefits - Book III - X",
      "length": 1045,
      "mode": "type"
    },
    {
      "id": "358",
      "title": "On Benefits - Book III - XI",
      "length": 1822,
      "mode": "type"
    },
    {
      "id": "359",
      "title": "On Benefits - Book III - XII",
      "length": 1841,
      "mode": "type"
    },
    {
      "id": "360",
      "title": "On Benefits - Book III - XIII",
      "length": 847,
      "mode": "type"
    },
    {
      "id": "361",
      "title": "On Benefits - Book III - XIV",
      "length": 1439,
      "mode": "type"
    },
    {
      "id": "362",
      "title": "On Benefits - Book III - XV",
      "length": 1681,
      "mode": "type"
    },
    {
      "id": "363",
      "title": "On Benefits - Book III - XVI",
      "length": 1679,
      "mode": "type"
    },
    {
      "id": "364",
      "title": "On Benefits - Book III - XVII",
      "length": 1982,
      "mode": "type"
    },
    {
      "id": "365",
      "title": "On Benefits - Book III - XVIII",
      "length": 2144,
      "mode": "type"
    },
    {
      "id": "366",
      "title": "On Benefits - Book III - XIX",
      "length": 2182,
      "mode": "type"
    },
    {
      "id": "367",
      "title": "On Benefits - Book III - XX",
      "length": 836,
      "mode": "type"
    },
    {
      "id": "368",
      "title": "On Benefits - Book III - XXI",
      "length": 949,
      "mode": "type"
    },
    {
      "id": "369",
      "title": "On Benefits - Book III - XXII",
      "length": 1479,
      "mode": "type"
    },
    {
      "id": "370",
      "title": "On Benefits - Book III - XXIII",
      "length": 2652,
      "mode": "type"
    },
    {
      "id": "371",
      "title": "On Benefits - Book III - XXIV",
      "length": 646,
      "mode": "type"
    },
    {
      "id": "372",
      "title": "On Benefits - Book III - XXV",
      "length": 625,
      "mode": "type"
    },
    {
      "id": "373",
      "title": "On Benefits - Book III - XXVI",
      "length": 1224,
      "mode": "type"
    },
    {
      "id": "374",
      "title": "On Benefits - Book III - XXVII",
      "length": 1594,
      "mode": "type"
    },
    {
      "id": "375",
      "title": "On Benefits - Book III - XXVIII",
      "length": 2381,
      "mode": "type"
    },
    {
      "id": "376",
      "title": "On Benefits - Book III - XXIX",
      "length": 3345,
      "mode": "type"
    },
    {
      "id": "377",
      "title": "On Benefits - Book III - XXX",
      "length": 1928,
      "mode": "type"
    },
    {
      "id": "378",
      "title": "On Benefits - Book III - XXXI",
      "length": 1906,
      "mode": "type"
    },
    {
      "id": "379",
      "title": "On Benefits - Book III - XXXII",
      "length": 2527,
      "mode": "type"
    },
    {
      "id": "380",
      "title": "On Benefits - Book III - XXXIII",
      "length": 2391,
      "mode": "type"
    },
    {
      "id": "381",
      "title": "On Benefits - Book III - XXXIV",
      "length": 719,
      "mode": "type"
    },
    {
      "id": "382",
      "title": "On Benefits - Book III - XXXV",
      "length": 2220,
      "mode": "type"
    },
    {
      "id": "383",
      "title": "On Benefits - Book III - XXXVI",
      "length": 1358,
      "mode": "type"
    },
    {
      "id": "384",
      "title": "On Benefits - Book III - XXXVII",
      "length": 2254,
      "mode": "type"
    },
    {
      "id": "385",
      "title": "On Benefits - Book III - XXXVIII",
      "length": 1127,
      "mode": "type"
    },
    {
      "id": "386",
      "title": "On Benefits - Book IV - I",
      "length": 1608,
      "mode": "type"
    },
    {
      "id": "387",
      "title": "On Benefits - Book IV - II",
      "length": 1484,
      "mode": "type"
    },
    {
      "id": "388",
      "title": "On Benefits - Book IV - III",
      "length": 1592,
      "mode": "type"
    },
    {
      "id": "389",
      "title": "On Benefits - Book IV - IV",
      "length": 1447,
      "mode": "type"
    },
    {
      "id": "390",
      "title": "On Benefits - Book IV - V",
      "length": 1433,
      "mode": "type"
    },
    {
      "id": "391",
      "title": "On Benefits - Book IV - VI",
      "length": 2960,
      "mode": "type"
    },
    {
      "id": "392",
      "title": "On Benefits - Book IV - VII",
      "length": 948,
      "mode": "type"
    },
    {
      "id": "393",
      "title": "On Benefits - Book IV - VIII",
      "length": 1322,
      "mode": "type"
    },
    {
      "id": "394",
      "title": "On Benefits - Book IV - IX",
      "length": 1418,
      "mode": "type"
    },
    {
      "id": "395",
      "title": "On Benefits - Book IV - X",
      "length": 1712,
      "mode": "type"
    },
    {
      "id": "396",
      "title": "On Benefits - Book IV - XI",
      "length": 2801,
      "mode": "type"
    },
    {
      "id": "397",
      "title": "On Benefits - Book IV - XII",
      "length": 2616,
      "mode": "type"
    },
    {
      "id": "398",
      "title": "On Benefits - Book IV - XIII",
      "length": 1471,
      "mode": "type"
    },
    {
      "id": "399",
      "title": "On Benefits - Book IV - XIV",
      "length": 1491,
      "mode": "type"
    },
    {
      "id": "400",
      "title": "On Benefits - Book IV - XV",
      "length": 1655,
      "mode": "type"
    },
    {
      "id": "401",
      "title": "On Benefits - Book IV - XVI",
      "length": 1404,
      "mode": "type"
    },
    {
      "id": "402",
      "title": "On Benefits - Book IV - XVII",
      "length": 2214,
      "mode": "type"
    },
    {
      "id": "403",
      "title": "On Benefits - Book IV - XVIII",
      "length": 1802,
      "mode": "type"
    },
    {
      "id": "404",
      "title": "On Benefits - Book IV - XIX",
      "length": 1450,
      "mode": "type"
    },
    {
      "id": "405",
      "title": "On Benefits - Book IV - XX",
      "length": 1349,
      "mode": "type"
    },
    {
      "id": "406",
      "title": "On Benefits - Book IV - XXI",
      "length": 3068,
      "mode": "type"
    },
    {
      "id": "407",
      "title": "On Benefits - Book IV - XXII",
      "length": 1597,
      "mode": "type"
    },
    {
      "id": "408",
      "title": "On Benefits - Book IV - XXIII",
      "length": 1736,
      "mode": "type"
    },
    {
      "id": "409",
      "title": "On Benefits - Book IV - XXIV",
      "length": 1306,
      "mode": "type"
    },
    {
      "id": "410",
      "title": "On Benefits - Book IV - XXV",
      "length": 970,
      "mode": "type"
    },
    {
      "id": "411",
      "title": "On Benefits - Book IV - XXVI",
      "length": 1563,
      "mode": "type"
    },
    {
      "id": "412",
      "title": "On Benefits - Book IV - XXVII",
      "length": 2280,
      "mode": "type"
    },
    {
      "id": "413",
      "title": "On Benefits - Book IV - XXVIII",
      "length": 2694,
      "mode": "type"
    },
    {
      "id": "414",
      "title": "On Benefits - Book IV - XXIX",
      "length": 1447,
      "mode": "type"
    },
    {
      "id": "415",
      "title": "On Benefits - Book IV - XXX",
      "length": 1716,
      "mode": "type"
    },
    {
      "id": "416",
      "title": "On Benefits - Book IV - XXXI",
      "length": 1094,
      "mode": "type"
    },
    {
      "id": "417",
      "title": "On Benefits - Book IV - XXXII",
      "length": 2327,
      "mode": "type"
    },
    {
      "id": "418",
      "title": "On Benefits - Book IV - XXXIII",
      "length": 1343,
      "mode": "type"
    },
    {
      "id": "419",
      "title": "On Benefits - Book IV - XXXIV",
      "length": 2710,
      "mode": "type"
    },
    {
      "id": "420",
      "title": "On Benefits - Book IV - XXXV",
      "length": 1571,
      "mode": "type"
    },
    {
      "id": "421",
      "title": "On Benefits - Book IV - XXXVI",
      "length": 1384,
      "mode": "type"
    },
    {
      "id": "422",
      "title": "On Benefits - Book IV - XXXVII",
      "length": 2450,
      "mode": "type"
    },
    {
      "id": "423",
      "title": "On Benefits - Book IV - XXXVIII",
      "length": 1347,
      "mode": "type"
    },
    {
      "id": "424",
      "title": "On Benefits - Book IV - XXXIX",
      "length": 2100,
      "mode": "type"
    },
    {
      "id": "425",
      "title": "On Benefits - Book IV - XL",
      "length": 2386,
      "mode": "type"
    },
    {
      "id": "426",
      "title": "On Benefits - Book V - I",
      "length": 2429,
      "mode": "type"
    },
    {
      "id": "427",
      "title": "On Benefits - Book V - II",
      "length": 1836,
      "mode": "type"
    },
    {
      "id": "428",
      "title": "On Benefits - Book V - III",
      "length": 1790,
      "mode": "type"
    },
    {
      "id": "429",
      "title": "On Benefits - Book V - IV",
      "length": 2005,
      "mode": "type"
    },
    {
      "id": "430",
      "title": "On Benefits - Book V - V",
      "length": 2262,
      "mode": "type"
    },
    {
      "id": "431",
      "title": "On Benefits - Book V - VI",
      "length": 4291,
      "mode": "type"
    },
    {
      "id": "432",
      "title": "On Benefits - Book V - VII",
      "length": 2861,
      "mode": "type"
    },
    {
      "id": "433",
      "title": "On Benefits - Book V - VIII",
      "length": 2718,
      "mode": "type"
    },
    {
      "id": "434",
      "title": "On Benefits - Book V - IX",
      "length": 2415,
      "mode": "type"
    },
    {
      "id": "435",
      "title": "On Benefits - Book V - X",
      "length": 2038,
      "mode": "type"
    },
    {
      "id": "436",
      "title": "On Benefits - Book V - XI",
      "length": 2480,
      "mode": "type"
    },
    {
      "id": "437",
      "title": "On Benefits - Book V - XII",
      "length": 3495,
      "mode": "type"
    },
    {
      "id": "438",
      "title": "On Benefits - Book V - XIII",
      "length": 1954,
      "mode": "type"
    },
    {
      "id": "439",
      "title": "On Benefits - Book V - XIV",
      "length": 1642,
      "mode": "type"
    },
    {
      "id": "440",
      "title": "On Benefits - Book V - XV",
      "length": 2333,
      "mode": "type"
    },
    {
      "id": "441",
      "title": "On Benefits - Book V - XVI",
      "length": 3344,
      "mode": "type"
    },
    {
      "id": "442",
      "title": "On Benefits - Book V - XVII",
      "length": 2792,
      "mode": "type"
    },
    {
      "id": "443",
      "title": "On Benefits - Book V - XVIII",
      "length": 952,
      "mode": "type"
    },
    {
      "id": "444",
      "title": "On Benefits - Book V - XIX",
      "length": 4963,
      "mode": "type"
    },
    {
      "id": "445",
      "title": "On Benefits - Book V - XX",
      "length": 3889,
      "mode": "type"
    },
    {
      "id": "446",
      "title": "On Benefits - Book V - XXI",
      "length": 1446,
      "mode": "type"
    },
    {
      "id": "447",
      "title": "On Benefits - Book V - XXII",
      "length": 1919,
      "mode": "type"
    },
    {
      "id": "448",
      "title": "On Benefits - Book V - XXIII",
      "length": 1149,
      "mode": "type"
    },
    {
      "id": "449",
      "title": "On Benefits - Book V - XXIV",
      "length": 1552,
      "mode": "type"
    },
    {
      "id": "450",
      "title": "On Benefits - Book V - XXV",
      "length": 3063,
      "mode": "type"
    },
    {
      "id": "451",
      "title": "On Benefits - Book VI - I",
      "length": 771,
      "mode": "type"
    },
    {
      "id": "452",
      "title": "On Benefits - Book VI - II",
      "length": 1443,
      "mode": "type"
    },
    {
      "id": "453",
      "title": "On Benefits - Book VI - III",
      "length": 1824,
      "mode": "type"
    },
    {
      "id": "454",
      "title": "On Benefits - Book VI - IV",
      "length": 3465,
      "mode": "type"
    },
    {
      "id": "455",
      "title": "On Benefits - Book VI - V",
      "length": 2103,
      "mode": "type"
    },
    {
      "id": "456",
      "title": "On Benefits - Book VI - VI",
      "length": 1245,
      "mode": "type"
    },
    {
      "id": "457",
      "title": "On Benefits - Book VI - VII",
      "length": 2547,
      "mode": "type"
    },
    {
      "id": "458",
      "title": "On Benefits - Book VI - VIII",
      "length": 1884,
      "mode": "type"
    },
    {
      "id": "459",
      "title": "On Benefits - Book VI - IX",
      "length": 1403,
      "mode": "type"
    },
    {
      "id": "460",
      "title": "On Benefits - Book VI - X",
      "length": 964,
      "mode": "type"
    },
    {
      "id": "461",
      "title": "On Benefits - Book VI - XI",
      "length": 1771,
      "mode": "type"
    },
    {
      "id": "462",
      "title": "On Benefits - Book VI - XII",
      "length": 1204,
      "mode": "type"
    },
    {
      "id": "463",
      "title": "On Benefits - Book VI - XIII",
      "length": 2154,
      "mode": "type"
    },
    {
      "id": "464",
      "title": "On Benefits - Book VI - XIV",
      "length": 1285,
      "mode": "type"
    },
    {
      "id": "465",
      "title": "On Benefits - Book VI - XV",
      "length": 3034,
      "mode": "type"
    },
    {
      "id": "466",
      "title": "On Benefits - Book VI - XVI",
      "length": 2667,
      "mode": "type"
    },
    {
      "id": "467",
      "title": "On Benefits - Book VI - XVII",
      "length": 642,
      "mode": "type"
    },
    {
      "id": "468",
      "title": "On Benefits - Book VI - XVIII",
      "length": 781,
      "mode": "type"
    },
    {
      "id": "469",
      "title": "On Benefits - Book VI - XIX",
      "length": 2380,
      "mode": "type"
    },
    {
      "id": "470",
      "title": "On Benefits - Book VI - XX",
      "length": 740,
      "mode": "type"
    },
    {
      "id": "471",
      "title": "On Benefits - Book VI - XXI",
      "length": 1737,
      "mode": "type"
    },
    {
      "id": "472",
      "title": "On Benefits - Book VI - XXII",
      "length": 1151,
      "mode": "type"
    },
    {
      "id": "473",
      "title": "On Benefits - Book VI - XXIII",
      "length": 4120,
      "mode": "type"
    },
    {
      "id": "474",
      "title": "On Benefits - Book VI - XXIV",
      "length": 765,
      "mode": "type"
    },
    {
      "id": "475",
      "title": "On Benefits - Book VI - XXV",
      "length": 2088,
      "mode": "type"
    },
    {
      "id": "476",
      "title": "On Benefits - Book VI - XXVI",
      "length": 1156,
      "mode": "type"
    },
    {
      "id": "477",
      "title": "On Benefits - Book VI - XXVII",
      "length": 3267,
      "mode": "type"
    },
    {
      "id": "478",
      "title": "On Benefits - Book VI - XXVIII",
      "length": 943,
      "mode": "type"
    },
    {
      "id": "479",
      "title": "On Benefits - Book VI - XXIX",
      "length": 1477,
      "mode": "type"
    },
    {
      "id": "480",
      "title": "On Benefits - Book VI - XXX",
      "length": 2668,
      "mode": "type"
    },
    {
      "id": "481",
      "title": "On Benefits - Book VI - XXXI",
      "length": 4212,
      "mode": "type"
    },
    {
      "id": "482",
      "title": "On Benefits - Book VI - XXXII",
      "length": 1663,
      "mode": "type"
    },
    {
      "id": "483",
      "title": "On Benefits - Book VI - XXXIII",
      "length": 1442,
      "mode": "type"
    },
    {
      "id": "484",
      "title": "On Benefits - Book VI - XXXIV",
      "length": 1704,
      "mode": "type"
    },
    {
      "id": "485",
      "title": "On Benefits - Book VI - XXXV",
      "length": 2765,
      "mode": "type"
    },
    {
      "id": "486",
      "title": "On Benefits - Book VI - XXXVI",
      "length": 998,
      "mode": "type"
    },
    {
      "id": "487",
      "title": "On Benefits - Book VI - XXXVII",
      "length": 1412,
      "mode": "type"
    },
    {
      "id": "488",
      "title": "On Benefits - Book VI - XXXVIII",
      "length": 2593,
      "mode": "type"
    },
    {
      "id": "489",
      "title": "On Benefits - Book VI - XXXIX",
      "length": 778,
      "mode": "type"
    },
    {
      "id": "490",
      "title": "On Benefits - Book VI - XL",
      "length": 1014,
      "mode": "type"
    },
    {
      "id": "491",
      "title": "On Benefits - Book VI - XLI",
      "length": 1188,
      "mode": "type"
    },
    {
      "id": "492",
      "title": "On Benefits - Book VI - XLII",
      "length": 1272,
      "mode": "type"
    },
    {
      "id": "493",
      "title": "On Benefits - Book VI - XLIII",
      "length": 1596,
      "mode": "type"
    },
    {
      "id": "494",
      "title": "On Benefits - Book VII - I",
      "length": 4014,
      "mode": "type"
    },
    {
      "id": "495",
      "title": "On Benefits - Book VII - II",
      "length": 3129,
      "mode": "type"
    },
    {
      "id": "496",
      "title": "On Benefits - Book VII - III",
      "length": 1628,
      "mode": "type"
    },
    {
      "id": "497",
      "title": "On Benefits - Book VII - IV",
      "length": 3333,
      "mode": "type"
    },
    {
      "id": "498",
      "title": "On Benefits - Book VII - V",
      "length": 1406,
      "mode": "type"
    },
    {
      "id": "499",
      "title": "On Benefits - Book VII - VI",
      "length": 1310,
      "mode": "type"
    },
    {
      "id": "500",
      "title": "On Benefits - Book VII - VII",
      "length": 2477,
      "mode": "type"
    },
    {
      "id": "501",
      "title": "On Benefits - Book VII - VIII",
      "length": 1465,
      "mode": "type"
    },
    {
      "id": "502",
      "title": "On Benefits - Book VII - IX",
      "length": 2113,
      "mode": "type"
    },
    {
      "id": "503",
      "title": "On Benefits - Book VII - X",
      "length": 2339,
      "mode": "type"
    },
    {
      "id": "504",
      "title": "On Benefits - Book VII - XI",
      "length": 569,
      "mode": "type"
    },
    {
      "id": "505",
      "title": "On Benefits - Book VII - XII",
      "length": 2283,
      "mode": "type"
    },
    {
      "id": "506",
      "title": "On Benefits - Book VII - XIII",
      "length": 376,
      "mode": "type"
    },
    {
      "id": "507",
      "title": "On Benefits - Book VII - XIV",
      "length": 3071,
      "mode": "type"
    },
    {
      "id": "508",
      "title": "On Benefits - Book VII - XV",
      "length": 2332,
      "mode": "type"
    },
    {
      "id": "509",
      "title": "On Benefits - Book VII - XVI",
      "length": 2721,
      "mode": "type"
    },
    {
      "id": "510",
      "title": "On Benefits - Book VII - XVII",
      "length": 757,
      "mode": "type"
    },
    {
      "id": "511",
      "title": "On Benefits - Book VII - XVIII",
      "length": 854,
      "mode": "type"
    },
    {
      "id": "512",
      "title": "On Benefits - Book VII - XIX",
      "length": 4430,
      "mode": "type"
    },
    {
      "id": "513",
      "title": "On Benefits - Book VII - XX",
      "length": 2080,
      "mode": "type"
    },
    {
      "id": "514",
      "title": "On Benefits - Book VII - XXI",
      "length": 1179,
      "mode": "type"
    },
    {
      "id": "515",
      "title": "On Benefits - Book VII - XXII",
      "length": 1119,
      "mode": "type"
    },
    {
      "id": "516",
      "title": "On Benefits - Book VII - XXIII",
      "length": 1459,
      "mode": "type"
    },
    {
      "id": "517",
      "title": "On Benefits - Book VII - XXIV",
      "length": 759,
      "mode": "type"
    },
    {
      "id": "518",
      "title": "On Benefits - Book VII - XXV",
      "length": 1208,
      "mode": "type"
    },
    {
      "id": "519",
      "title": "On Benefits - Book VII - XXVI",
      "length": 2479,
      "mode": "type"
    },
    {
      "id": "520",
      "title": "On Benefits - Book VII - XXVII",
      "length": 1597,
      "mode": "type"
    },
    {
      "id": "521",
      "title": "On Benefits - Book VII - XXVIII",
      "length": 1940,
      "mode": "type"
    },
    {
      "id": "522",
      "title": "On Benefits - Book VII - XXIX",
      "length": 911,
      "mode": "type"
    },
    {
      "id": "523",
      "title": "On Benefits - Book VII - XXX",
      "length": 1278,
      "mode": "type"
    },
    {
      "id": "524",
      "title": "On Benefits - Book VII - XXXI",
      "length": 2548,
      "mode": "type"
    },
    {
      "id": "525",
      "title": "On Benefits - Book VII - XXXII",
      "length": 647,
      "mode": "type"
    },
    {
      "id": "526",
      "title": "Endnotes",
      "length": 22967,
      "mode": "hide"
    },
    {
      "id": "527",
      "title": "Colophon",
      "length": 1193,
      "mode": "hide"
    },
    {
      "id": "528",
      "title": "Uncopyright",
      "length": 2050,
      "mode": "hide"
    }
  ],
  "openlibraryId": "OL27292247W",
  "goodreadsId": "1933080",
  "rating": 0.8619999999999999,
  "popularity": 1113,
  "cover": null,
  "free": false,
  "custom": false,
  "createdAt": 1721490115254
}